[
  {
    "code": "01",
    "label": "36\""
  },
  {
    "code": "02",
    "label": "26\""
  },
  {
    "code": "03",
    "label": "17-1/2\""
  },
  {
    "code": "04",
    "label": "12-1/4\""
  },
  {
    "code": "05",
    "label": "8-3/4\""
  },
  {
    "code": "06",
    "label": "8-1/2\""
  },
  {
    "code": "07",
    "label": "6-1/8\""
  },
  {
    "code": "08",
    "label": "6\""
  },
  {
    "code": "09",
    "label": "5-7/8\""
  },
  {
    "code": "10",
    "label": "4-1/8\""
  },
  {
    "code": "11",
    "label": "2-3/4\""
  },
  {
    "code": "12",
    "label": "8-3/8\""
  },
  {
    "code": "13",
    "label": "8-3/32\""
  },
  {
    "code": "14",
    "label": "4-1/4\""
  },
  {
    "code": "15",
    "label": "7\""
  },
  {
    "code": "16",
    "label": "12-1/2\""
  },
  {
    "code": "17",
    "label": "6-3/32\""
  }
]